authz_sample.py
test_sdk_samples.py
tokenizer_sample.py
userstore_sample.py
usercloudssdk/__init__.py
usercloudssdk/asyncclient.py
usercloudssdk/client.py
usercloudssdk/client_helpers.py
usercloudssdk/client_test.py
usercloudssdk/constants.py
usercloudssdk/data_types.py
usercloudssdk/errors.py
usercloudssdk/models.py
usercloudssdk/policies.py
usercloudssdk/token.py
usercloudssdk/uchttpclient.py
usercloudssdk/ucjson.py
usercloudssdk-1.11.0.dist-info/LICENSE
usercloudssdk-1.11.0.dist-info/METADATA
usercloudssdk-1.11.0.dist-info/WHEEL
usercloudssdk-1.11.0.dist-info/top_level.txt
usercloudssdk-1.11.0.dist-info/RECORD
