Metadata-Version: 2.2
Name: usercloudssdk
Version: 1.11.0
Summary: Python SDK for UserClouds
Author-email: UserClouds <info@userclouds.com>
License: The MIT License
Project-URL: Homepage, https://github.com/userclouds/sdk-python
Project-URL: Documentation, https://docs.userclouds.com/
Project-URL: Source, https://github.com/userclouds/sdk-python
Project-URL: Changelog, https://github.com/userclouds/sdk-python/blob/main/CHANGELOG.md
Classifier: Development Status :: 4 - Beta
Classifier: Intended Audience :: Developers
Classifier: Programming Language :: Python :: 3 :: Only
Classifier: Programming Language :: Python :: 3.9
Classifier: Programming Language :: Python :: 3.10
Classifier: Programming Language :: Python :: 3.11
License-File: LICENSE
Requires-Dist: certifi>=2023.7.2
Requires-Dist: charset-normalizer>=2.1.1
Requires-Dist: idna>=3.4
Requires-Dist: iso8601>=1.1.0
Requires-Dist: pycparser>=2.21
Requires-Dist: PyJWT>=2.6.0
Requires-Dist: httpx>=0.25.0
Requires-Dist: urllib3>=1.26.12
